README.md
setup.py
src/rnaseq_lib3/__init__.py
src/rnaseq_lib3.egg-info/PKG-INFO
src/rnaseq_lib3.egg-info/SOURCES.txt
src/rnaseq_lib3.egg-info/dependency_links.txt
src/rnaseq_lib3.egg-info/requires.txt
src/rnaseq_lib3.egg-info/top_level.txt
src/rnaseq_lib3/dimensionality_reduction/__init__.py
src/rnaseq_lib3/dimensionality_reduction/trimap.py
src/rnaseq_lib3/exp/__init__.py
src/rnaseq_lib3/gtf/__init__.py
src/rnaseq_lib3/kegg/__init__.py
src/rnaseq_lib3/math/__init__.py
src/rnaseq_lib3/plot/__init__.py
src/rnaseq_lib3/plot/exp/__init__.py
src/rnaseq_lib3/synapse/__init__.py
src/rnaseq_lib3/tcga/__init__.py
src/rnaseq_lib3/tcga/pathway.py
src/rnaseq_lib3/tcga/snv.py
src/rnaseq_lib3/utils/__init__.py