Metadata-Version: 1.0
Name: rnaseq-lib3
Version: 1.0a1
Summary: Library of convenience functions related to current research
Home-page: http://github.com/jvivian/rnaseq-lib3
Author: John Vivian
Author-email: jtvivian@gmail.com
License: MIT
Platform: UNKNOWN
